morphUz/__init__.py
morfoUz_kutubxona-3.2.dist-info/LICENSE.txt
morfoUz_kutubxona-3.2.dist-info/METADATA
morfoUz_kutubxona-3.2.dist-info/WHEEL
morfoUz_kutubxona-3.2.dist-info/top_level.txt
morfoUz_kutubxona-3.2.dist-info/RECORD
