Metadata-Version: 2.1
Name: morfoUz_kutubxona
Version: 3.2
Summary: ushbu kutubxona o`zbek tili uchun qo`llaniladi. 
Author: Alisher Ismailov Shakirovich
Author-email: alisherismailov1991@gmail.com
License: MIT
Classifier: Programming Language :: Python :: 3
Classifier: License :: OSI Approved :: MIT License
Classifier: Operating System :: OS Independent
License-File: LICENSE.txt
